bedhandler/__init__.py
bedhandler/domain/__init__.py
bedhandler/domain/base.py
bedhandler/domain/geneid.py
bedhandler/domain/pools.py
bedhandler/domain/regionid.py
bedhandler/domain/submitted_region.py
bedhandler/handler/__init__.py
bedhandler/handler/loader.py
bedhandler/mapper/__init__.py
bedhandler/mapper/base.py
bedhandler/mapper/geneidmapper.py
bedhandler/mapper/poolmapper.py
bedhandler/mapper/regionidmapper.py
bedhandler/mapper/submitted_region_mapper.py
test/__init__.py
test/domain/__init__.py
test/domain/test_base.py
test/domain/test_regionid.py
test/handler/__init__.py
test/handler/test_loader.py
test/mapper/__init__.py
test/mapper/test_base.py
test/mapper/test_geneid_mapper.py
test/mapper/test_pool_mapper.py
test/mapper/test_region_id_mapper.py
test/mapper/test_submitted_region_mapper.py
bedhandler-1.0.0b3.dist-info/LICENSE
bedhandler-1.0.0b3.dist-info/METADATA
bedhandler-1.0.0b3.dist-info/WHEEL
bedhandler-1.0.0b3.dist-info/top_level.txt
bedhandler-1.0.0b3.dist-info/RECORD
